{"stat.useItem.minecraft.command_block":5,"stat.useItem.minecraft.lapis_block":2,"stat.walkOneCm":922347,"stat.leaveGame":351,"stat.useItem.minecraft.beacon":1,"stat.jump":3893,"stat.swimOneCm":4882,"stat.fallOneCm":108468,"stat.useItem.minecraft.redstone_block":8,"stat.crouchOneCm":8095,"stat.useItem.minecraft.redstone_torch":6,"stat.useItem.minecraft.leaves":15,"stat.useItem.minecraft.dirt":66,"stat.sprintOneCm":565839,"stat.useItem.minecraft.diamond_block":9,"stat.useItem.minecraft.stained_glass":2,"achievement.exploreAllBiomes":{"value":0,"progress":["Plains","The End"]},"stat.useItem.minecraft.stone_slab":1,"achievement.openInventory":10,"stat.flyOneCm":1967728,"stat.playOneMinute":461755,"stat.timeSinceDeath":461755,"stat.diveOneCm":16601}